junshan_kit/BenchmarkFunctions.py
junshan_kit/Check_Info.py
junshan_kit/DataHub.py
junshan_kit/DataProcessor.py
junshan_kit/DataSets.py
junshan_kit/Evaluate_Metrics.py
junshan_kit/FiguresHub.py
junshan_kit/FiguresLab.py
junshan_kit/ModelsHub.py
junshan_kit/ParametersHub.py
junshan_kit/PlotUtils.py
junshan_kit/Print_Info.py
junshan_kit/TrainingHub.py
junshan_kit/__init__.py
junshan_kit/kit.py
junshan_kit/OptimizerHup/OptimizerFactory.py
junshan_kit/OptimizerHup/SPBM.py
junshan_kit/OptimizerHup/SPBM_func.py
junshan_kit/OptimizerHup/__init__.py
junshan_kit-2.8.40.dist-info/METADATA
junshan_kit-2.8.40.dist-info/WHEEL
junshan_kit-2.8.40.dist-info/RECORD
