Metadata-Version: 2.4
Name: junshan_kit
Version: 2.8.40
Summary: This is an optimization tool.
Author-email: Junshan Yin <junshanyin@163.com>
Requires-Dist: cvxpy==1.6.5
Requires-Dist: kaggle==1.7.4.5
Requires-Dist: kagglehub==0.3.13
Requires-Dist: matplotlib==3.10.3
Requires-Dist: numpy==2.2.6
Requires-Dist: openml==0.15.1
Requires-Dist: scikit-learn==1.7.1
Requires-Dist: selenium==4.36.0
Requires-Dist: torch==2.6.0
Requires-Dist: torchvision==0.21.0
